palette/__init__.py
palette/extractor.py
pixelpalette-1.0.0.dist-info/METADATA
pixelpalette-1.0.0.dist-info/WHEEL
pixelpalette-1.0.0.dist-info/top_level.txt
pixelpalette-1.0.0.dist-info/RECORD
