Metadata-Version: 2.1
Name: pixelpalette
Version: 1.0.0
Summary: A package to extract dominant colors from images and represent them in RGB, Hex, and HSL formats.
Home-page: https://github.com/imparth7/pixelpalette
Author: Parth Dudhatra
Author-email: imparth.dev@gmail.com
License: MIT
Project-URL: Bug Tracker, https://github.com/imparth7/pixelpalette/issues
Project-URL: Source Code, https://github.com/imparth7/pixelpalette
Keywords: color extraction,image processing,dominant colors,RGB to Hex,RGB to HSLcolor palettes,image analysis
Platform: Any
Classifier: Programming Language :: Python :: 3
Classifier: License :: OSI Approved :: MIT License
Classifier: Operating System :: OS Independent
Classifier: Topic :: Multimedia :: Graphics
Classifier: Intended Audience :: Developers
Classifier: Natural Language :: English
Requires-Python: >=3.6
Requires-Dist: numpy
Requires-Dist: matplotlib
Requires-Dist: scikit-learn
